Metadata-Version: 1.0
Name: protocol-scraper
Version: 1.2
Summary: Python CLI for automatically writing protocols.
Home-page: https://github.com/J-E-J-S/protocol-scraper
Author: James Sanders
Author-email: james.sanders1711@gmail.com
License: UNKNOWN
Platform: UNKNOWN
